ovos_stt_http_server/__init__.py
ovos_stt_http_server/__main__.py
ovos_stt_http_server/gradio_app.py
ovos_stt_http_server/version.py
ovos_stt_http_server/audio/ca.mp3
ovos_stt_http_server/audio/de.mp3
ovos_stt_http_server/audio/en.mp3
ovos_stt_http_server/audio/es.mp3
ovos_stt_http_server/audio/fr.mp3
ovos_stt_http_server/audio/it.mp3
ovos_stt_http_server/audio/nl.mp3
ovos_stt_http_server/audio/pt.mp3
ovos_stt_http_server/audio/uk.mp3
ovos_stt_http_server-0.1.4.dist-info/LICENSE.md
ovos_stt_http_server-0.1.4.dist-info/METADATA
ovos_stt_http_server-0.1.4.dist-info/WHEEL
ovos_stt_http_server-0.1.4.dist-info/entry_points.txt
ovos_stt_http_server-0.1.4.dist-info/top_level.txt
ovos_stt_http_server-0.1.4.dist-info/zip-safe
ovos_stt_http_server-0.1.4.dist-info/RECORD
