Metadata-Version: 2.1
Name: ovos-stt-http-server
Version: 0.1.4
Summary: simple aiohttp server to host OpenVoiceOS stt plugins as a service
Home-page: https://github.com/OpenVoiceOS/ovos-stt-http-server
Author: JarbasAi
Author-email: jarbasai@mailfence.com
License: Apache-2.0
Keywords: plugin STT OVOS OpenVoiceOS
Classifier: Development Status :: 3 - Alpha
Classifier: Intended Audience :: Developers
Classifier: Topic :: Text Processing :: Linguistic
Classifier: License :: OSI Approved :: Apache Software License
Classifier: Programming Language :: Python :: 2
Classifier: Programming Language :: Python :: 2.7
Classifier: Programming Language :: Python :: 3
Classifier: Programming Language :: Python :: 3.0
Classifier: Programming Language :: Python :: 3.1
Classifier: Programming Language :: Python :: 3.2
Classifier: Programming Language :: Python :: 3.3
Classifier: Programming Language :: Python :: 3.4
Classifier: Programming Language :: Python :: 3.5
Classifier: Programming Language :: Python :: 3.6
License-File: LICENSE.md
Requires-Dist: ovos-plugin-manager<1.0.0,>=0.7.0
Requires-Dist: fastapi~=0.95
Requires-Dist: uvicorn~=0.22
Requires-Dist: gradio~=3.28
Requires-Dist: ovos-utils<1.0.0,>=0.0.32
Requires-Dist: flask
